README.txt
setup.py
reqhash/__init__.py
reqhash/parser.py
reqhash.egg-info/PKG-INFO
reqhash.egg-info/SOURCES.txt
reqhash.egg-info/dependency_links.txt
reqhash.egg-info/entry_points.txt
reqhash.egg-info/top_level.txt