Metadata-Version: 1.0
Name: reqhash
Version: 0.1.1
Summary: Calculate a hash value over a requirement file.
Home-page: https://github.com/dhepper/reqhash
Author: Daniel Hepper
Author-email: daniel@butfriendly.com
License: UNKNOWN
Platform: UNKNOWN
